cafe/__init__.py
cafe/database/__init__.py
cafe/database/sqlalchemy/__init__.py
cafe/database/sqlalchemy/declarative.py
cafe/database/sqlalchemy/migration.py
cafe/database/sqlalchemy/postgres.py
cafe/database/sqlalchemy/session.py
python_cafe_sqlalchemy-0.4.0.dist-info/DESCRIPTION.rst
python_cafe_sqlalchemy-0.4.0.dist-info/METADATA
python_cafe_sqlalchemy-0.4.0.dist-info/RECORD
python_cafe_sqlalchemy-0.4.0.dist-info/WHEEL
python_cafe_sqlalchemy-0.4.0.dist-info/metadata.json
python_cafe_sqlalchemy-0.4.0.dist-info/top_level.txt
